joistpy/__init__.py
joistpy/joistpy.py
joistpy/property files/K_L_360.csv
joistpy/property files/K_Total.csv
joistpy/property files/K_weight.csv
joistpy/property files/KCS_L_360.csv
joistpy/property files/KCS_shear_capacity.csv
joistpy/property files/KCS_Total.csv
joistpy/property files/KCS_weight.csv
joistpy-1.1.0.dist-info/LICENSE
joistpy-1.1.0.dist-info/METADATA
joistpy-1.1.0.dist-info/WHEEL
joistpy-1.1.0.dist-info/RECORD
