Metadata-Version: 2.1
Name: joistpy
Version: 1.1.0
Summary: JoistPy is a library that acts as a database for SJI steel open web bar joist shapes for easy use in structural calculations.
License: MIT
Author: Matthew Upshaw
Author-email: matthew.upshaw02@gmail.com
Requires-Python: >=3.10,<4.0
Classifier: License :: OSI Approved :: MIT License
Classifier: Programming Language :: Python :: 3
Classifier: Programming Language :: Python :: 3.10
Classifier: Programming Language :: Python :: 3.11
Classifier: Programming Language :: Python :: 3.12
Requires-Dist: numpy (==1.26.4)
Requires-Dist: pandas (==2.2.2)
